streampipes/__init__.py
streampipes/__version__.py
streampipes/client/__init__.py
streampipes/client/client.py
streampipes/client/config.py
streampipes/client/credential_provider.py
streampipes/endpoint/__init__.py
streampipes/endpoint/api/__init__.py
streampipes/endpoint/api/data_lake_measure.py
streampipes/endpoint/api/data_stream.py
streampipes/endpoint/api/version.py
streampipes/endpoint/endpoint.py
streampipes/endpoint/exceptions.py
streampipes/endpoint/messaging/__init__.py
streampipes/function_zoo/__init__.py
streampipes/function_zoo/river_function.py
streampipes/functions/__init__.py
streampipes/functions/broker/__init__.py
streampipes/functions/broker/broker.py
streampipes/functions/broker/broker_handler.py
streampipes/functions/broker/consumer.py
streampipes/functions/broker/kafka/__init__.py
streampipes/functions/broker/kafka/kafka_consumer.py
streampipes/functions/broker/kafka/kafka_message_fetcher.py
streampipes/functions/broker/kafka/kafka_publisher.py
streampipes/functions/broker/nats/__init__.py
streampipes/functions/broker/nats/nats_consumer.py
streampipes/functions/broker/nats/nats_publisher.py
streampipes/functions/broker/output_collector.py
streampipes/functions/broker/publisher.py
streampipes/functions/function_handler.py
streampipes/functions/registration.py
streampipes/functions/streampipes_function.py
streampipes/functions/utils/__init__.py
streampipes/functions/utils/async_iter_handler.py
streampipes/functions/utils/data_stream_context.py
streampipes/functions/utils/data_stream_generator.py
streampipes/functions/utils/function_context.py
streampipes/model/__init__.py
streampipes/model/common.py
streampipes/model/container/__init__.py
streampipes/model/container/data_lake_measures.py
streampipes/model/container/data_streams.py
streampipes/model/container/resource_container.py
streampipes/model/container/versions.py
streampipes/model/resource/__init__.py
streampipes/model/resource/data_lake_measure.py
streampipes/model/resource/data_series.py
streampipes-0.98.0.dist-info/METADATA
streampipes-0.98.0.dist-info/WHEEL
streampipes-0.98.0.dist-info/RECORD
