Metadata-Version: 2.1
Name: streampipes
Version: 0.98.0
Summary: Python library for Apache StreamPipes
Home-page: https://streampipes.apache.org/docs/docs/python/latest/
License: Apache 2.0
Keywords: streampipes,iot,iiot,analytics,stream-processing,apache
Author: Apache Software Foundation
Author-email: dev@streampipes.apache.org
Requires-Python: >=3.10,<3.14
Classifier: Development Status :: 4 - Beta
Classifier: Environment :: Console
Classifier: Intended Audience :: Developers
Classifier: Intended Audience :: Information Technology
Classifier: Intended Audience :: Manufacturing
Classifier: License :: Other/Proprietary License
Classifier: Operating System :: OS Independent
Classifier: Programming Language :: Python :: 3
Classifier: Programming Language :: Python :: 3.10
Classifier: Programming Language :: Python :: 3.11
Classifier: Topic :: Scientific/Engineering
Requires-Dist: confluent-kafka (>=2.0.2,<3)
Requires-Dist: nats-py (>=2.2,<3)
Requires-Dist: pandas (>=2.3,<3)
Requires-Dist: pydantic (>=2.6.3,<3)
Requires-Dist: requests (>=2.28,<3)
Requires-Dist: typing-extensions (>=4.5,<5)
Project-URL: Documentation, https://streampipes.apache.org/docs/docs/python/latest/
Project-URL: Repository, https://github.com/apache/streampipes
